ArimaTP/__init__.py
ArimaTP/version.py
ArimaTP-1.0.0.dist-info/LICENSE
ArimaTP-1.0.0.dist-info/METADATA
ArimaTP-1.0.0.dist-info/WHEEL
ArimaTP-1.0.0.dist-info/top_level.txt
ArimaTP-1.0.0.dist-info/zip-safe
ArimaTP-1.0.0.dist-info/RECORD
