Metadata-Version: 2.1
Name: ArimaTP
Version: 1.0.0
Summary: Python 3 library for short text
Home-page: https://github.com/alexjszamora78
Author: RayServer
Author-email: alexjszamora78@gmail.com
License: The Unlicense (Unlicense)
Keywords: chatbot,torch,IA
Classifier: Development Status :: 5 - Production/Stable
Classifier: Environment :: Console
Classifier: Intended Audience :: Developers
Classifier: License :: OSI Approved :: The Unlicense (Unlicense)
Classifier: Natural Language :: English
Classifier: Operating System :: OS Independent
Classifier: Programming Language :: Python :: 3.6
Classifier: Programming Language :: Python :: 3.7
Classifier: Programming Language :: Python :: 3.8
Classifier: Programming Language :: Python :: 3.9
Classifier: Programming Language :: Python
Classifier: Topic :: Internet
Classifier: Topic :: Software Development :: Libraries :: Python Modules
Classifier: Topic :: Utilities
License-File: LICENSE
Requires-Dist: pyro-ppl >=1.9.1
Requires-Dist: dill
